{
    "name": "PWE",
    "version": "1.0",
    "download_url": "https://github.com/Scorpion2on/PWE/archive/1.0.zip",

    "homepage": "https://warsawexpo.eu",
    "requires": "4.5",
    "tested": "4.8",
    "last_updated": "2020-04-02 16:17:00",
    "upgrade_notice": "1.0 upgrade...",

    "author": "PWE Dev",
    "author_homepage": "https://warsawexpo.eu",

    "sections": {
        "description": "(Required) Plugin description. Basic HTML can be used in all sections.",
        "installation": "(Recommended) Installation instructions.",
        "changelog": "(Recommended) Changelog. <p>This section will be displayed by default when the user clicks 'View version x.y.z details'.</p>",
        "custom_section": "This is a custom section labeled 'Custom Section'."
    },

    "icons": {
        "1x": "https://github.com/Scorpion2on/PWE/blob/1.0/icon.png",
        "2x": "https://github.com/Scorpion2on/PWE/blob/1.0/icon.png"
    },

    "banners": {
        "low": "http://w-shadow.com/files/external-update-example/assets/banner-772x250.png",
        "high": "http://w-shadow.com/files/external-update-example/assets/banner-1544x500.png"
    },

    "translations": [{
            "language": "pl_PL",
            "version": "1.0",
            "updated": "2020-04-02 16:17:00",
            "package": "http://example.com/updates/translations/french-language-pack.zip"
        },
        {
            "language": "de_DE",
            "version": "5.0",
            "updated": "2016-04-22 23:22:42",
            "package": "http://example.com/updates/translations/german-language-pack.zip"
        }
    ],

    "rating": 90,
    "num_ratings": 123,

    "downloaded": 1234,
    "active_installs": 12345
}